{
  "generated_at": "2026-03-12T22:07:56.279Z",
  "timezone": "America/New_York",
  "weather": {
    "summary": "light rain",
    "temp_f": 36,
    "feels_like_f": 28,
    "five_day": [
      {
        "day": "Thu",
        "summary": "Rain",
        "high_f": 39,
        "low_f": 37
      },
      {
        "day": "Fri",
        "summary": "Clouds",
        "high_f": 43,
        "low_f": 43
      },
      {
        "day": "Sat",
        "summary": "Clouds",
        "high_f": 44,
        "low_f": 44
      },
      {
        "day": "Sun",
        "summary": "Clouds",
        "high_f": 45,
        "low_f": 45
      },
      {
        "day": "Mon",
        "summary": "Rain",
        "high_f": 55,
        "low_f": 55
      }
    ]
  },
  "headlines": [
    {
      "title": "Backstage At The Paramount With Nymphia Wind & Plastique Tiara",
      "url": "https://coveteur.com/nymphia-wind-plastique-tiara-interview",
      "source": "Coveteur.com"
    },
    {
      "title": "Film Fans in New York City Are About to Get a Massive Treat, Care of the Inaugural Art House Cinema Week",
      "url": "https://www.indiewire.com/news/general-news/art-house-cinema-week-new-york-1235183567/",
      "source": "IndieWire"
    },
    {
      "title": "SXSW 2026 Curtain Raiser: 21 Films To Get Excited About At This Year's Festival",
      "url": "https://screenanarchy.com/2026/03/sxsw-2026-curtain-raiser-21-films-to-get-excited-about-at-this-years-festival-gallery.html",
      "source": "Screenanarchy.com"
    },
    {
      "title": "This Week In Rust: This Week in Rust 642",
      "url": "https://this-week-in-rust.org/blog/2026/03/11/this-week-in-rust-642/",
      "source": "This-week-in-rust.org"
    },
    {
      "title": "Best New R&B/Hip-Hop Songs: Nia Smith, Marlon Craft, Skrilla & More",
      "url": "http://www.billboard.com/lists/rb-hip-hop-fresh-picks-nia-smith-ama-marlon-craft-skrilla/",
      "source": "Billboard"
    }
  ],
  "featured_tonight": [
    {
      "title": "Wicked (NY)",
      "venue": "Gershwin Theatre",
      "borough": "New York",
      "start_iso": "2026-03-12T23:00:00Z",
      "time_window": "7:00 PM",
      "url": "https://www.ticketmaster.com/wicked-ny-new-york-new-york-03-12-2026/event/Z1r9uZrrZbpZ1AvpKFd",
      "booking_url": "https://www.ticketmaster.com/wicked-ny-new-york-new-york-03-12-2026/event/Z1r9uZrrZbpZ1AvpKFd",
      "price": "",
      "category": "Arts & Theatre",
      "source_name": "Ticketmaster",
      "source_url": "https://www.ticketmaster.com/wicked-ny-new-york-new-york-03-12-2026/event/Z1r9uZrrZbpZ1AvpKFd",
      "image_url": "https://s1.ticketm.net/dam/a/963/bdfc3e57-f001-4729-9424-53d9ad83c963_TABLET_LANDSCAPE_16_9.jpg"
    },
    {
      "title": "Noah Pope, Renny Conti, James Eichman",
      "venue": "Mercury Lounge",
      "borough": "New York",
      "start_iso": "2026-03-12T22:00:00Z",
      "time_window": "6:00 PM",
      "url": "https://www.ticketmaster.com/noah-pope-renny-conti-james-eichman-new-york-new-york-03-12-2026/event/0000644BCF08C0B3",
      "booking_url": "https://www.ticketmaster.com/noah-pope-renny-conti-james-eichman-new-york-new-york-03-12-2026/event/0000644BCF08C0B3",
      "price": "",
      "category": "Music",
      "source_name": "Ticketmaster",
      "source_url": "https://www.ticketmaster.com/noah-pope-renny-conti-james-eichman-new-york-new-york-03-12-2026/event/0000644BCF08C0B3",
      "image_url": "https://s1.ticketm.net/dam/e/0b3/047069b8-b1a9-419f-9af5-a4c3910510b3_RETINA_PORTRAIT_3_2.jpg"
    },
    {
      "title": "Death Becomes Her",
      "venue": "Lunt-Fontanne Theatre",
      "borough": "New York",
      "start_iso": "2026-03-12T23:00:00Z",
      "time_window": "7:00 PM",
      "url": "https://www.ticketmaster.com/death-becomes-her-new-york-new-york-03-12-2026/event/Z1r9uZrrZbpZ1Av4Ebb",
      "booking_url": "https://www.ticketmaster.com/death-becomes-her-new-york-new-york-03-12-2026/event/Z1r9uZrrZbpZ1Av4Ebb",
      "price": "",
      "category": "Arts & Theatre",
      "source_name": "Ticketmaster",
      "source_url": "https://www.ticketmaster.com/death-becomes-her-new-york-new-york-03-12-2026/event/Z1r9uZrrZbpZ1Av4Ebb",
      "image_url": "https://s1.ticketm.net/dam/a/62a/cbfce925-8919-4c5f-9efb-9472f842e62a_SOURCE"
    }
  ],
  "featured_verified": [],
  "picks_from_sources": [
    {
      "title": "DJ Raphi's 2026 USA Hype Tour",
      "venue": "Gramercy Theatre",
      "borough": "New York",
      "start_iso": "2026-03-12T21:00:00Z",
      "time_window": "5:00 PM",
      "url": "https://www.ticketmaster.com/dj-raphis-2026-usa-hype-tour-new-york-new-york-03-12-2026/event/0000634AC76A68E5",
      "price": "",
      "category": "Music",
      "source_name": "Ticketmaster",
      "source_url": "https://www.ticketmaster.com/dj-raphis-2026-usa-hype-tour-new-york-new-york-03-12-2026/event/0000634AC76A68E5",
      "image_url": "https://s1.ticketm.net/dam/a/61a/cf30062f-92a9-4e88-9b9c-6636c900061a_TABLET_LANDSCAPE_16_9.jpg"
    },
    {
      "title": "Burnout Paradise",
      "venue": "Astor Place Theatre",
      "borough": "New York",
      "start_iso": "2026-03-12T21:00:00Z",
      "time_window": "5:00 PM",
      "url": "https://www.ticketmaster.com/burnout-paradise-new-york-new-york-03-12-2026/event/03006367F9752C60",
      "price": "",
      "category": "Arts & Theatre",
      "source_name": "Ticketmaster",
      "source_url": "https://www.ticketmaster.com/burnout-paradise-new-york-new-york-03-12-2026/event/03006367F9752C60",
      "image_url": "https://s1.ticketm.net/dam/a/2e2/9c60c02c-69d7-417f-a4d1-98e2635d52e2_ARTIST_PAGE_3_2.jpg"
    },
    {
      "title": "The High Society New Orleans Jazz Band",
      "venue": "Birdland Theater",
      "borough": "New York",
      "start_iso": "2026-03-12T21:30:00Z",
      "time_window": "5:30 PM",
      "url": "https://www.ticketweb.com/event/the-high-society-new-orleans-birdland-theater-tickets/14714403",
      "price": "$0–$0",
      "category": "Music",
      "source_name": "Ticketmaster",
      "source_url": "https://www.ticketweb.com/event/the-high-society-new-orleans-birdland-theater-tickets/14714403",
      "image_url": "https://s1.ticketm.net/dam/c/779/d4bc7e11-1b50-4aa4-a2be-0a21569f5779_106531_RETINA_LANDSCAPE_16_9.jpg"
    },
    {
      "title": "Noah Pope, Renny Conti, James Eichman",
      "venue": "Mercury Lounge",
      "borough": "New York",
      "start_iso": "2026-03-12T22:00:00Z",
      "time_window": "6:00 PM",
      "url": "https://www.ticketmaster.com/noah-pope-renny-conti-james-eichman-new-york-new-york-03-12-2026/event/0000644BCF08C0B3",
      "price": "",
      "category": "Music",
      "source_name": "Ticketmaster",
      "source_url": "https://www.ticketmaster.com/noah-pope-renny-conti-james-eichman-new-york-new-york-03-12-2026/event/0000644BCF08C0B3",
      "image_url": "https://s1.ticketm.net/dam/e/0b3/047069b8-b1a9-419f-9af5-a4c3910510b3_RETINA_PORTRAIT_3_2.jpg"
    },
    {
      "title": "Stranger Things: The First Shadow",
      "venue": "Marquis Theatre",
      "borough": "New York",
      "start_iso": "2026-03-12T23:00:00Z",
      "time_window": "7:00 PM",
      "url": "https://www.ticketmaster.com/stranger-things-the-first-shadow-new-york-new-york-03-12-2026/event/Z1r9uZrrZbpZ1Av-6Ab",
      "price": "",
      "category": "Arts & Theatre",
      "source_name": "Ticketmaster",
      "source_url": "https://www.ticketmaster.com/stranger-things-the-first-shadow-new-york-new-york-03-12-2026/event/Z1r9uZrrZbpZ1Av-6Ab",
      "image_url": "https://s1.ticketm.net/dam/a/650/bf4f4e8b-b847-41b3-82ac-b826aad3c650_CUSTOM.jpg"
    },
    {
      "title": "Death Becomes Her",
      "venue": "Lunt-Fontanne Theatre",
      "borough": "New York",
      "start_iso": "2026-03-12T23:00:00Z",
      "time_window": "7:00 PM",
      "url": "https://www.ticketmaster.com/death-becomes-her-new-york-new-york-03-12-2026/event/Z1r9uZrrZbpZ1Av4Ebb",
      "price": "",
      "category": "Arts & Theatre",
      "source_name": "Ticketmaster",
      "source_url": "https://www.ticketmaster.com/death-becomes-her-new-york-new-york-03-12-2026/event/Z1r9uZrrZbpZ1Av4Ebb",
      "image_url": "https://s1.ticketm.net/dam/a/62a/cbfce925-8919-4c5f-9efb-9472f842e62a_SOURCE"
    },
    {
      "title": "Six (New York, NY)",
      "venue": "Lena Horne Theatre",
      "borough": "New York",
      "start_iso": "2026-03-12T23:00:00Z",
      "time_window": "7:00 PM",
      "url": "https://www.ticketmaster.com/six-new-york-ny-new-york-new-york-03-12-2026/event/Z1r9uZrrZbpZ1AvjPfb",
      "price": "",
      "category": "Arts & Theatre",
      "source_name": "Ticketmaster",
      "source_url": "https://www.ticketmaster.com/six-new-york-ny-new-york-new-york-03-12-2026/event/Z1r9uZrrZbpZ1AvjPfb",
      "image_url": "https://s1.ticketm.net/dam/a/26a/ae570422-5c6d-401a-8dae-8545b131126a_1248581_TABLET_LANDSCAPE_3_2.jpg"
    },
    {
      "title": "Wicked (NY)",
      "venue": "Gershwin Theatre",
      "borough": "New York",
      "start_iso": "2026-03-12T23:00:00Z",
      "time_window": "7:00 PM",
      "url": "https://www.ticketmaster.com/wicked-ny-new-york-new-york-03-12-2026/event/Z1r9uZrrZbpZ1AvpKFd",
      "price": "",
      "category": "Arts & Theatre",
      "source_name": "Ticketmaster",
      "source_url": "https://www.ticketmaster.com/wicked-ny-new-york-new-york-03-12-2026/event/Z1r9uZrrZbpZ1AvpKFd",
      "image_url": "https://s1.ticketm.net/dam/a/963/bdfc3e57-f001-4729-9424-53d9ad83c963_TABLET_LANDSCAPE_16_9.jpg"
    },
    {
      "title": "MJ",
      "venue": "Neil Simon Theatre",
      "borough": "New York",
      "start_iso": "2026-03-12T23:00:00Z",
      "time_window": "7:00 PM",
      "url": "https://www.ticketmaster.com/mj-new-york-new-york-03-12-2026/event/Z1r9uZrrZbpZ1Avqaj3",
      "price": "",
      "category": "Arts & Theatre",
      "source_name": "Ticketmaster",
      "source_url": "https://www.ticketmaster.com/mj-new-york-new-york-03-12-2026/event/Z1r9uZrrZbpZ1Avqaj3",
      "image_url": "https://s1.ticketm.net/dam/a/cfd/122be1ff-687b-4676-87de-65fb2a07ecfd_1248631_CUSTOM.jpg"
    },
    {
      "title": "Hamilton (NY)",
      "venue": "Richard Rodgers Theatre",
      "borough": "New York",
      "start_iso": "2026-03-12T23:00:00Z",
      "time_window": "7:00 PM",
      "url": "https://www.ticketmaster.com/hamilton-ny-new-york-new-york-03-12-2026/event/Z1r9uZrrZbpZ1Avqd7s",
      "price": "",
      "category": "Arts & Theatre",
      "source_name": "Ticketmaster",
      "source_url": "https://www.ticketmaster.com/hamilton-ny-new-york-new-york-03-12-2026/event/Z1r9uZrrZbpZ1Avqd7s",
      "image_url": "https://s1.ticketm.net/dam/a/00f/b9aebee0-d1cb-4a5c-8e0e-0ca03fd4d00f_ARTIST_PAGE_3_2.jpg"
    },
    {
      "title": "The Lion King (New York, NY)",
      "venue": "Minskoff Theatre",
      "borough": "New York",
      "start_iso": "2026-03-12T23:00:00Z",
      "time_window": "7:00 PM",
      "url": "https://www.ticketmaster.com/the-lion-king-new-york-ny-new-york-new-york-03-12-2026/event/Z1r9uZrrZbpZ1AvrpJo",
      "price": "",
      "category": "Arts & Theatre",
      "source_name": "Ticketmaster",
      "source_url": "https://www.ticketmaster.com/the-lion-king-new-york-ny-new-york-new-york-03-12-2026/event/Z1r9uZrrZbpZ1AvrpJo",
      "image_url": "https://s1.ticketm.net/dam/a/7ae/48ba24c8-7e1c-4830-bff1-ad8451b847ae_SOURCE"
    },
    {
      "title": "Arthur Miller's Death of a Salesman",
      "venue": "Winter Garden Theatre",
      "borough": "New York",
      "start_iso": "2026-03-12T23:00:00Z",
      "time_window": "7:00 PM",
      "url": "https://www.ticketmaster.com/arthur-millers-death-of-a-salesman-new-york-new-york-03-12-2026/event/Z1r9uZruZqGZ17JAvg",
      "price": "",
      "category": "Arts & Theatre",
      "source_name": "Ticketmaster",
      "source_url": "https://www.ticketmaster.com/arthur-millers-death-of-a-salesman-new-york-new-york-03-12-2026/event/Z1r9uZruZqGZ17JAvg",
      "image_url": "https://s1.ticketm.net/dam/a/e97/fb152039-f4ae-4191-aaf7-334c83419e97_RECOMENDATION_16_9.jpg"
    },
    {
      "title": "The Banksy Museum New York - March Trivia Night",
      "venue": "Banksy Museum New York",
      "borough": "New York",
      "start_iso": "2026-03-12T21:00:00Z",
      "time_window": "5:00 PM",
      "url": "https://www.universe.com/events/the-banksy-museum-new-york-march-trivia-night-tickets-CFLTP2?ref=ticketmaster",
      "price": "",
      "category": "culture",
      "source_name": "Ticketmaster",
      "source_url": "https://www.universe.com/events/the-banksy-museum-new-york-march-trivia-night-tickets-CFLTP2?ref=ticketmaster",
      "image_url": "https://images.universe.com/a436950c-7421-4b30-89a4-e1dc58367e8e/-/resize/1200x/-/crop/1200x1200/0,251/-/format/jpeg/-/scale_crop/1024x576/center/-/progressive/yes/-/inline/yes/"
    },
    {
      "title": "BIG EAST Men's Basketball Tournament Session 3: Quarterfinal Doublehdr",
      "venue": "Madison Square Garden",
      "borough": "New York",
      "start_iso": "2026-03-12T23:00:00Z",
      "time_window": "7:00 PM",
      "url": "https://www.ticketmaster.com/big-east-mens-basketball-tournament-session-new-york-new-york-03-12-2026/event/3B00636ED6EB5EDD",
      "price": "",
      "category": "Sports",
      "source_name": "Ticketmaster",
      "source_url": "https://www.ticketmaster.com/big-east-mens-basketball-tournament-session-new-york-new-york-03-12-2026/event/3B00636ED6EB5EDD",
      "image_url": "https://s1.ticketm.net/dam/a/f29/7b496df8-bcba-4884-a995-d01eacdd0f29_911021_EVENT_DETAIL_PAGE_16_9.jpg"
    },
    {
      "title": "MOCA PERFORMS - Declaration of Independence, Day 2",
      "venue": "Museum of Chinese in America",
      "borough": "New York",
      "start_iso": "2026-03-12T23:00:00Z",
      "time_window": "7:00 PM",
      "url": "https://www.universe.com/events/moca-performs-declaration-of-independence-day-2-tickets-D3M1PV?ref=ticketmaster",
      "price": "",
      "category": "Miscellaneous",
      "source_name": "Ticketmaster",
      "source_url": "https://www.universe.com/events/moca-performs-declaration-of-independence-day-2-tickets-D3M1PV?ref=ticketmaster",
      "image_url": "https://s1.ticketm.net/dam/c/03e/e15ef00f-2c87-4421-ae61-d740851a703e_105891_TABLET_LANDSCAPE_LARGE_16_9.jpg"
    },
    {
      "title": "Jamie Allan's Amaze",
      "venue": "New World Stages - Stage 5",
      "borough": "New York",
      "start_iso": "2026-03-12T23:00:00Z",
      "time_window": "7:00 PM",
      "url": "https://www.ticketmaster.com/jamie-allans-amaze-new-york-new-york-03-12-2026/event/Z1r9uZruZqGZ17JAoa",
      "price": "",
      "category": "Miscellaneous",
      "source_name": "Ticketmaster",
      "source_url": "https://www.ticketmaster.com/jamie-allans-amaze-new-york-new-york-03-12-2026/event/Z1r9uZruZqGZ17JAoa",
      "image_url": "https://s1.ticketm.net/dam/a/f9c/09610a49-d4a3-462a-93aa-f6f5df63ef9c_TABLET_LANDSCAPE_LARGE_16_9.jpg"
    },
    {
      "title": "Banksy Museum - Flexiticket",
      "venue": "Banksy Museum New York",
      "borough": "New York",
      "start_iso": "2026-03-12T14:00:00Z",
      "time_window": "10:00 AM",
      "url": "https://www.universe.com/events/banksy-museum-flexiticket-tickets-F7XJ8T?ref=ticketmaster",
      "price": "",
      "category": "Arts & Theatre",
      "source_name": "Ticketmaster",
      "source_url": "https://www.universe.com/events/banksy-museum-flexiticket-tickets-F7XJ8T?ref=ticketmaster",
      "image_url": "https://s1.ticketm.net/dam/a/438/d47dcb31-a7ee-4820-aa73-cc46f2473438_TABLET_LANDSCAPE_16_9.jpg"
    },
    {
      "title": "Pen Pals",
      "venue": "DR2",
      "borough": "New York",
      "start_iso": "2026-03-12T17:00:00Z",
      "time_window": "1:00 PM",
      "url": "https://www.ticketmaster.com/pen-pals-new-york-new-york-03-12-2026/event/Z1r9uZruZqGZ17JAuE",
      "price": "",
      "category": "Arts & Theatre",
      "source_name": "Ticketmaster",
      "source_url": "https://www.ticketmaster.com/pen-pals-new-york-new-york-03-12-2026/event/Z1r9uZruZqGZ17JAuE",
      "image_url": "https://s1.ticketm.net/dam/a/72f/5e873588-e208-4d7e-9f38-c9caaaa1b72f_EVENT_DETAIL_PAGE_16_9.jpg"
    },
    {
      "title": "The Outsiders",
      "venue": "Bernard B. Jacobs Theatre",
      "borough": "New York",
      "start_iso": "2026-03-12T17:00:00Z",
      "time_window": "1:00 PM",
      "url": "https://www.ticketmaster.com/the-outsiders-new-york-new-york-03-12-2026/event/Z1r9uZruZqGZ17PYrA",
      "price": "",
      "category": "Arts & Theatre",
      "source_name": "Ticketmaster",
      "source_url": "https://www.ticketmaster.com/the-outsiders-new-york-new-york-03-12-2026/event/Z1r9uZruZqGZ17PYrA",
      "image_url": "https://s1.ticketm.net/dam/a/24b/ab9bc062-6e29-42eb-9131-3cb9efdb324b_RETINA_PORTRAIT_3_2.jpg"
    },
    {
      "title": "The Banksy Museum New York!",
      "venue": "Banksy Museum New York",
      "borough": "New York",
      "start_iso": "2026-03-12T17:30:00Z",
      "time_window": "1:30 PM",
      "url": "https://www.universe.com/events/the-banksy-museum-new-york-tickets-5PKNY0?ref=ticketmaster",
      "price": "",
      "category": "Arts & Theatre",
      "source_name": "Ticketmaster",
      "source_url": "https://www.universe.com/events/the-banksy-museum-new-york-tickets-5PKNY0?ref=ticketmaster",
      "image_url": "https://s1.ticketm.net/dam/a/438/d47dcb31-a7ee-4820-aa73-cc46f2473438_TABLET_LANDSCAPE_16_9.jpg"
    },
    {
      "title": "Singfeld! A Musical About Nothing!",
      "venue": "The Theater Center",
      "borough": "New York",
      "start_iso": "2026-03-12T18:00:00Z",
      "time_window": "2:00 PM",
      "url": "https://www.ticketmaster.com/singfeld-a-musical-about-nothing-new-york-new-york-03-12-2026/event/3000637880C41F48",
      "price": "",
      "category": "Arts & Theatre",
      "source_name": "Ticketmaster",
      "source_url": "https://www.ticketmaster.com/singfeld-a-musical-about-nothing-new-york-new-york-03-12-2026/event/3000637880C41F48",
      "image_url": "https://s1.ticketm.net/dam/a/111/5a7ae98c-0e1b-4cf1-8d79-86466a845111_TABLET_LANDSCAPE_16_9.jpg"
    },
    {
      "title": "Heathers: The Musical",
      "venue": "New World Stages - Stage 1",
      "borough": "New York",
      "start_iso": "2026-03-12T18:00:00Z",
      "time_window": "2:00 PM",
      "url": "https://www.ticketmaster.com/heathers-the-musical-new-york-new-york-03-12-2026/event/Z1r9uZruZqGZ17J7bF",
      "price": "",
      "category": "Arts & Theatre",
      "source_name": "Ticketmaster",
      "source_url": "https://www.ticketmaster.com/heathers-the-musical-new-york-new-york-03-12-2026/event/Z1r9uZruZqGZ17J7bF",
      "image_url": "https://s1.ticketm.net/dam/a/a60/9e821b33-dcf1-4da3-9669-b5100aa88a60_RETINA_PORTRAIT_3_2.jpg"
    },
    {
      "title": "The Play That Goes Wrong",
      "venue": "New World Stages - Stage 4",
      "borough": "New York",
      "start_iso": "2026-03-12T18:00:00Z",
      "time_window": "2:00 PM",
      "url": "https://www.ticketmaster.com/the-play-that-goes-wrong-new-york-new-york-03-12-2026/event/Z1r9uZruZqGZ17JvC8",
      "price": "",
      "category": "Arts & Theatre",
      "source_name": "Ticketmaster",
      "source_url": "https://www.ticketmaster.com/the-play-that-goes-wrong-new-york-new-york-03-12-2026/event/Z1r9uZruZqGZ17JvC8",
      "image_url": "https://s1.ticketm.net/dam/a/3ef/25ca9f7f-06e3-4065-bcc4-6223a20c43ef_RECOMENDATION_16_9.jpg"
    },
    {
      "title": "The Great Gatsby",
      "venue": "Broadway Theatre",
      "borough": "New York",
      "start_iso": "2026-03-12T18:00:00Z",
      "time_window": "2:00 PM",
      "url": "https://www.ticketmaster.com/the-great-gatsby-new-york-new-york-03-12-2026/event/Z1r9uZruZqGZ17PsbS",
      "price": "",
      "category": "Arts & Theatre",
      "source_name": "Ticketmaster",
      "source_url": "https://www.ticketmaster.com/the-great-gatsby-new-york-new-york-03-12-2026/event/Z1r9uZruZqGZ17PsbS",
      "image_url": "https://s1.ticketm.net/dam/a/16d/0eb1670e-3c8a-4e88-9953-f8584fb9a16d_EVENT_DETAIL_PAGE_16_9.jpg"
    },
    {
      "title": "The 25th Annual Putnam County Spelling Bee",
      "venue": "New World Stages - Stage 3",
      "borough": "New York",
      "start_iso": "2026-03-12T18:00:00Z",
      "time_window": "2:00 PM",
      "url": "https://www.ticketmaster.com/the-25th-annual-putnam-county-spelling-new-york-new-york-03-12-2026/event/Z1r9uZruZqGZ17PyP7",
      "price": "",
      "category": "Arts & Theatre",
      "source_name": "Ticketmaster",
      "source_url": "https://www.ticketmaster.com/the-25th-annual-putnam-county-spelling-new-york-new-york-03-12-2026/event/Z1r9uZruZqGZ17PyP7",
      "image_url": "https://s1.ticketm.net/dam/a/0fe/8c1d4514-1703-4a77-a2e5-2a8b8089c0fe_SOURCE"
    },
    {
      "title": "BIG EAST Men's Basketball Tournament Session 2: Quarterfinal Doublehdr",
      "venue": "Madison Square Garden",
      "borough": "New York",
      "start_iso": "2026-03-12T16:00:00Z",
      "time_window": "12:00 PM",
      "url": "https://www.ticketmaster.com/big-east-mens-basketball-tournament-session-new-york-new-york-03-12-2026/event/3B00636ED6D55ECF",
      "price": "",
      "category": "Sports",
      "source_name": "Ticketmaster",
      "source_url": "https://www.ticketmaster.com/big-east-mens-basketball-tournament-session-new-york-new-york-03-12-2026/event/3B00636ED6D55ECF",
      "image_url": "https://s1.ticketm.net/dam/a/f29/7b496df8-bcba-4884-a995-d01eacdd0f29_911021_EVENT_DETAIL_PAGE_16_9.jpg"
    },
    {
      "title": "Writer Patrick Lazour Will Star in Select Performances of His Night Side Songs",
      "venue": "Playbill",
      "borough": "NYC",
      "start_iso": "2026-03-12T20:29:00.000Z",
      "time_window": "4:29 PM",
      "url": "https://playbill.com/article/writer-patrick-lazour-will-star-in-select-performances-of-his-night-side-songs",
      "price": "",
      "category": "theater",
      "source_name": "Playbill",
      "source_url": "https://playbill.com/article/writer-patrick-lazour-will-star-in-select-performances-of-his-night-side-songs",
      "image_url": ""
    },
    {
      "title": "Bedlam to Stage 4-Person Version of Shakespeare’s Othello",
      "venue": "Playbill",
      "borough": "NYC",
      "start_iso": "2026-03-12T20:28:00.000Z",
      "time_window": "4:28 PM",
      "url": "https://playbill.com/article/bedlam-to-stage-4-person-version-of-shakespeares-othello",
      "price": "",
      "category": "theater",
      "source_name": "Playbill",
      "source_url": "https://playbill.com/article/bedlam-to-stage-4-person-version-of-shakespeares-othello",
      "image_url": ""
    },
    {
      "title": "If You Want to Get Called on at Every Brilliant Thing, Don't Be Too Eager, Says Daniel Radcliffe",
      "venue": "Playbill",
      "borough": "NYC",
      "start_iso": "2026-03-12T20:01:00.000Z",
      "time_window": "4:01 PM",
      "url": "https://playbill.com/article/if-you-want-to-get-called-on-at-every-brilliant-thing-dont-be-too-eager-says-daniel-radcliffe",
      "price": "",
      "category": "theater",
      "source_name": "Playbill",
      "source_url": "https://playbill.com/article/if-you-want-to-get-called-on-at-every-brilliant-thing-dont-be-too-eager-says-daniel-radcliffe",
      "image_url": ""
    },
    {
      "title": "Photos: Get a 1st Look at John Lithgow-Led Giant on Broadway",
      "venue": "Playbill",
      "borough": "NYC",
      "start_iso": "2026-03-12T19:42:00.000Z",
      "time_window": "3:42 PM",
      "url": "https://playbill.com/article/photos-get-a-1st-look-at-john-lithgow-led-giant-on-broadway",
      "price": "",
      "category": "theater",
      "source_name": "Playbill",
      "source_url": "https://playbill.com/article/photos-get-a-1st-look-at-john-lithgow-led-giant-on-broadway",
      "image_url": ""
    },
    {
      "title": "Cody Renard Richard, Herrick Goldman Appointed to Educational Theatre Foundation Board of Directors",
      "venue": "Playbill",
      "borough": "NYC",
      "start_iso": "2026-03-12T19:13:00.000Z",
      "time_window": "3:13 PM",
      "url": "https://playbill.com/article/cody-renard-richard-herrick-goldman-appointed-to-educational-theatre-foundation-board-of-directors",
      "price": "",
      "category": "theater",
      "source_name": "Playbill",
      "source_url": "https://playbill.com/article/cody-renard-richard-herrick-goldman-appointed-to-educational-theatre-foundation-board-of-directors",
      "image_url": ""
    },
    {
      "title": "King's Critique Musical Will Hold Another NYC Industry Reading",
      "venue": "Playbill",
      "borough": "NYC",
      "start_iso": "2026-03-12T19:08:00.000Z",
      "time_window": "3:08 PM",
      "url": "https://playbill.com/article/kings-critique-musical-will-hold-another-nyc-industry-reading",
      "price": "",
      "category": "theater",
      "source_name": "Playbill",
      "source_url": "https://playbill.com/article/kings-critique-musical-will-hold-another-nyc-industry-reading",
      "image_url": ""
    },
    {
      "title": "Jared Mezzocchi’s 73 Seconds Will Play Transformed Planetarium in Lower Eastside Girls Club",
      "venue": "Playbill",
      "borough": "NYC",
      "start_iso": "2026-03-12T18:56:00.000Z",
      "time_window": "2:56 PM",
      "url": "https://playbill.com/article/jared-mezzocchis-73-seconds-will-play-transformed-planetarium-in-lower-east-side-girls-club",
      "price": "",
      "category": "theater",
      "source_name": "Playbill",
      "source_url": "https://playbill.com/article/jared-mezzocchis-73-seconds-will-play-transformed-planetarium-in-lower-east-side-girls-club",
      "image_url": ""
    },
    {
      "title": "Charles Busch, John-Andrew Morrison, Mary Testa, Karen Ziemba Set for A Woman of No Importance",
      "venue": "Playbill",
      "borough": "NYC",
      "start_iso": "2026-03-12T17:59:00.000Z",
      "time_window": "1:59 PM",
      "url": "https://playbill.com/article/charles-busch-john-andrew-morrison-mary-testa-karen-ziemba-set-for-a-woman-of-no-importance",
      "price": "",
      "category": "theater",
      "source_name": "Playbill",
      "source_url": "https://playbill.com/article/charles-busch-john-andrew-morrison-mary-testa-karen-ziemba-set-for-a-woman-of-no-importance",
      "image_url": ""
    },
    {
      "title": "Roberta Colindrez Joins Last Summer at Bluefish Cove at Classic Stage",
      "venue": "Playbill",
      "borough": "NYC",
      "start_iso": "2026-03-12T16:42:00.000Z",
      "time_window": "12:42 PM",
      "url": "https://playbill.com/article/roberta-colindrez-joins-last-summer-at-bluefish-cove-at-classic-stage",
      "price": "",
      "category": "theater",
      "source_name": "Playbill",
      "source_url": "https://playbill.com/article/roberta-colindrez-joins-last-summer-at-bluefish-cove-at-classic-stage",
      "image_url": ""
    },
    {
      "title": "Ro Reddick Doesn't Mind If You Laugh During Cold War Choir Practice",
      "venue": "Playbill",
      "borough": "NYC",
      "start_iso": "2026-03-12T16:38:00.000Z",
      "time_window": "12:38 PM",
      "url": "https://playbill.com/article/ro-reddick-doesnt-mind-if-you-laugh-during-cold-war-choir-practice",
      "price": "",
      "category": "theater",
      "source_name": "Playbill",
      "source_url": "https://playbill.com/article/ro-reddick-doesnt-mind-if-you-laugh-during-cold-war-choir-practice",
      "image_url": ""
    },
    {
      "title": "Writer Patrick Lazour Will Star in Select Performances of His Night Side Songs",
      "venue": "Time Out",
      "borough": "NYC",
      "start_iso": "2026-03-12T20:29:00.000Z",
      "time_window": "4:29 PM",
      "url": "https://playbill.com/article/writer-patrick-lazour-will-star-in-select-performances-of-his-night-side-songs",
      "price": "",
      "category": "events",
      "source_name": "Time Out",
      "source_url": "https://playbill.com/article/writer-patrick-lazour-will-star-in-select-performances-of-his-night-side-songs",
      "image_url": ""
    },
    {
      "title": "Bedlam to Stage 4-Person Version of Shakespeare’s Othello",
      "venue": "Time Out",
      "borough": "NYC",
      "start_iso": "2026-03-12T20:28:00.000Z",
      "time_window": "4:28 PM",
      "url": "https://playbill.com/article/bedlam-to-stage-4-person-version-of-shakespeares-othello",
      "price": "",
      "category": "events",
      "source_name": "Time Out",
      "source_url": "https://playbill.com/article/bedlam-to-stage-4-person-version-of-shakespeares-othello",
      "image_url": ""
    },
    {
      "title": "If You Want to Get Called on at Every Brilliant Thing, Don't Be Too Eager, Says Daniel Radcliffe",
      "venue": "Time Out",
      "borough": "NYC",
      "start_iso": "2026-03-12T20:01:00.000Z",
      "time_window": "4:01 PM",
      "url": "https://playbill.com/article/if-you-want-to-get-called-on-at-every-brilliant-thing-dont-be-too-eager-says-daniel-radcliffe",
      "price": "",
      "category": "events",
      "source_name": "Time Out",
      "source_url": "https://playbill.com/article/if-you-want-to-get-called-on-at-every-brilliant-thing-dont-be-too-eager-says-daniel-radcliffe",
      "image_url": ""
    },
    {
      "title": "Photos: Get a 1st Look at John Lithgow-Led Giant on Broadway",
      "venue": "Time Out",
      "borough": "NYC",
      "start_iso": "2026-03-12T19:42:00.000Z",
      "time_window": "3:42 PM",
      "url": "https://playbill.com/article/photos-get-a-1st-look-at-john-lithgow-led-giant-on-broadway",
      "price": "",
      "category": "events",
      "source_name": "Time Out",
      "source_url": "https://playbill.com/article/photos-get-a-1st-look-at-john-lithgow-led-giant-on-broadway",
      "image_url": ""
    },
    {
      "title": "Cody Renard Richard, Herrick Goldman Appointed to Educational Theatre Foundation Board of Directors",
      "venue": "Time Out",
      "borough": "NYC",
      "start_iso": "2026-03-12T19:13:00.000Z",
      "time_window": "3:13 PM",
      "url": "https://playbill.com/article/cody-renard-richard-herrick-goldman-appointed-to-educational-theatre-foundation-board-of-directors",
      "price": "",
      "category": "events",
      "source_name": "Time Out",
      "source_url": "https://playbill.com/article/cody-renard-richard-herrick-goldman-appointed-to-educational-theatre-foundation-board-of-directors",
      "image_url": ""
    },
    {
      "title": "King's Critique Musical Will Hold Another NYC Industry Reading",
      "venue": "Time Out",
      "borough": "NYC",
      "start_iso": "2026-03-12T19:08:00.000Z",
      "time_window": "3:08 PM",
      "url": "https://playbill.com/article/kings-critique-musical-will-hold-another-nyc-industry-reading",
      "price": "",
      "category": "events",
      "source_name": "Time Out",
      "source_url": "https://playbill.com/article/kings-critique-musical-will-hold-another-nyc-industry-reading",
      "image_url": ""
    },
    {
      "title": "Jared Mezzocchi’s 73 Seconds Will Play Transformed Planetarium in Lower Eastside Girls Club",
      "venue": "Time Out",
      "borough": "NYC",
      "start_iso": "2026-03-12T18:56:00.000Z",
      "time_window": "2:56 PM",
      "url": "https://playbill.com/article/jared-mezzocchis-73-seconds-will-play-transformed-planetarium-in-lower-east-side-girls-club",
      "price": "",
      "category": "events",
      "source_name": "Time Out",
      "source_url": "https://playbill.com/article/jared-mezzocchis-73-seconds-will-play-transformed-planetarium-in-lower-east-side-girls-club",
      "image_url": ""
    },
    {
      "title": "Charles Busch, John-Andrew Morrison, Mary Testa, Karen Ziemba Set for A Woman of No Importance",
      "venue": "Time Out",
      "borough": "NYC",
      "start_iso": "2026-03-12T17:59:00.000Z",
      "time_window": "1:59 PM",
      "url": "https://playbill.com/article/charles-busch-john-andrew-morrison-mary-testa-karen-ziemba-set-for-a-woman-of-no-importance",
      "price": "",
      "category": "events",
      "source_name": "Time Out",
      "source_url": "https://playbill.com/article/charles-busch-john-andrew-morrison-mary-testa-karen-ziemba-set-for-a-woman-of-no-importance",
      "image_url": ""
    },
    {
      "title": "Roberta Colindrez Joins Last Summer at Bluefish Cove at Classic Stage",
      "venue": "Time Out",
      "borough": "NYC",
      "start_iso": "2026-03-12T16:42:00.000Z",
      "time_window": "12:42 PM",
      "url": "https://playbill.com/article/roberta-colindrez-joins-last-summer-at-bluefish-cove-at-classic-stage",
      "price": "",
      "category": "events",
      "source_name": "Time Out",
      "source_url": "https://playbill.com/article/roberta-colindrez-joins-last-summer-at-bluefish-cove-at-classic-stage",
      "image_url": ""
    },
    {
      "title": "Ro Reddick Doesn't Mind If You Laugh During Cold War Choir Practice",
      "venue": "Time Out",
      "borough": "NYC",
      "start_iso": "2026-03-12T16:38:00.000Z",
      "time_window": "12:38 PM",
      "url": "https://playbill.com/article/ro-reddick-doesnt-mind-if-you-laugh-during-cold-war-choir-practice",
      "price": "",
      "category": "events",
      "source_name": "Time Out",
      "source_url": "https://playbill.com/article/ro-reddick-doesnt-mind-if-you-laugh-during-cold-war-choir-practice",
      "image_url": ""
    },
    {
      "title": "Writer Patrick Lazour Will Star in Select Performances of His Night Side Songs",
      "venue": "Resident Advisor",
      "borough": "NYC",
      "start_iso": "2026-03-12T20:29:00.000Z",
      "time_window": "4:29 PM",
      "url": "https://playbill.com/article/writer-patrick-lazour-will-star-in-select-performances-of-his-night-side-songs",
      "price": "",
      "category": "nightlife",
      "source_name": "Resident Advisor",
      "source_url": "https://playbill.com/article/writer-patrick-lazour-will-star-in-select-performances-of-his-night-side-songs",
      "image_url": ""
    },
    {
      "title": "Bedlam to Stage 4-Person Version of Shakespeare’s Othello",
      "venue": "Resident Advisor",
      "borough": "NYC",
      "start_iso": "2026-03-12T20:28:00.000Z",
      "time_window": "4:28 PM",
      "url": "https://playbill.com/article/bedlam-to-stage-4-person-version-of-shakespeares-othello",
      "price": "",
      "category": "nightlife",
      "source_name": "Resident Advisor",
      "source_url": "https://playbill.com/article/bedlam-to-stage-4-person-version-of-shakespeares-othello",
      "image_url": ""
    },
    {
      "title": "If You Want to Get Called on at Every Brilliant Thing, Don't Be Too Eager, Says Daniel Radcliffe",
      "venue": "Resident Advisor",
      "borough": "NYC",
      "start_iso": "2026-03-12T20:01:00.000Z",
      "time_window": "4:01 PM",
      "url": "https://playbill.com/article/if-you-want-to-get-called-on-at-every-brilliant-thing-dont-be-too-eager-says-daniel-radcliffe",
      "price": "",
      "category": "nightlife",
      "source_name": "Resident Advisor",
      "source_url": "https://playbill.com/article/if-you-want-to-get-called-on-at-every-brilliant-thing-dont-be-too-eager-says-daniel-radcliffe",
      "image_url": ""
    },
    {
      "title": "Photos: Get a 1st Look at John Lithgow-Led Giant on Broadway",
      "venue": "Resident Advisor",
      "borough": "NYC",
      "start_iso": "2026-03-12T19:42:00.000Z",
      "time_window": "3:42 PM",
      "url": "https://playbill.com/article/photos-get-a-1st-look-at-john-lithgow-led-giant-on-broadway",
      "price": "",
      "category": "nightlife",
      "source_name": "Resident Advisor",
      "source_url": "https://playbill.com/article/photos-get-a-1st-look-at-john-lithgow-led-giant-on-broadway",
      "image_url": ""
    },
    {
      "title": "Cody Renard Richard, Herrick Goldman Appointed to Educational Theatre Foundation Board of Directors",
      "venue": "Resident Advisor",
      "borough": "NYC",
      "start_iso": "2026-03-12T19:13:00.000Z",
      "time_window": "3:13 PM",
      "url": "https://playbill.com/article/cody-renard-richard-herrick-goldman-appointed-to-educational-theatre-foundation-board-of-directors",
      "price": "",
      "category": "nightlife",
      "source_name": "Resident Advisor",
      "source_url": "https://playbill.com/article/cody-renard-richard-herrick-goldman-appointed-to-educational-theatre-foundation-board-of-directors",
      "image_url": ""
    },
    {
      "title": "King's Critique Musical Will Hold Another NYC Industry Reading",
      "venue": "Resident Advisor",
      "borough": "NYC",
      "start_iso": "2026-03-12T19:08:00.000Z",
      "time_window": "3:08 PM",
      "url": "https://playbill.com/article/kings-critique-musical-will-hold-another-nyc-industry-reading",
      "price": "",
      "category": "nightlife",
      "source_name": "Resident Advisor",
      "source_url": "https://playbill.com/article/kings-critique-musical-will-hold-another-nyc-industry-reading",
      "image_url": ""
    },
    {
      "title": "Jared Mezzocchi’s 73 Seconds Will Play Transformed Planetarium in Lower Eastside Girls Club",
      "venue": "Resident Advisor",
      "borough": "NYC",
      "start_iso": "2026-03-12T18:56:00.000Z",
      "time_window": "2:56 PM",
      "url": "https://playbill.com/article/jared-mezzocchis-73-seconds-will-play-transformed-planetarium-in-lower-east-side-girls-club",
      "price": "",
      "category": "nightlife",
      "source_name": "Resident Advisor",
      "source_url": "https://playbill.com/article/jared-mezzocchis-73-seconds-will-play-transformed-planetarium-in-lower-east-side-girls-club",
      "image_url": ""
    },
    {
      "title": "Charles Busch, John-Andrew Morrison, Mary Testa, Karen Ziemba Set for A Woman of No Importance",
      "venue": "Resident Advisor",
      "borough": "NYC",
      "start_iso": "2026-03-12T17:59:00.000Z",
      "time_window": "1:59 PM",
      "url": "https://playbill.com/article/charles-busch-john-andrew-morrison-mary-testa-karen-ziemba-set-for-a-woman-of-no-importance",
      "price": "",
      "category": "nightlife",
      "source_name": "Resident Advisor",
      "source_url": "https://playbill.com/article/charles-busch-john-andrew-morrison-mary-testa-karen-ziemba-set-for-a-woman-of-no-importance",
      "image_url": ""
    },
    {
      "title": "Roberta Colindrez Joins Last Summer at Bluefish Cove at Classic Stage",
      "venue": "Resident Advisor",
      "borough": "NYC",
      "start_iso": "2026-03-12T16:42:00.000Z",
      "time_window": "12:42 PM",
      "url": "https://playbill.com/article/roberta-colindrez-joins-last-summer-at-bluefish-cove-at-classic-stage",
      "price": "",
      "category": "nightlife",
      "source_name": "Resident Advisor",
      "source_url": "https://playbill.com/article/roberta-colindrez-joins-last-summer-at-bluefish-cove-at-classic-stage",
      "image_url": ""
    },
    {
      "title": "Ro Reddick Doesn't Mind If You Laugh During Cold War Choir Practice",
      "venue": "Resident Advisor",
      "borough": "NYC",
      "start_iso": "2026-03-12T16:38:00.000Z",
      "time_window": "12:38 PM",
      "url": "https://playbill.com/article/ro-reddick-doesnt-mind-if-you-laugh-during-cold-war-choir-practice",
      "price": "",
      "category": "nightlife",
      "source_name": "Resident Advisor",
      "source_url": "https://playbill.com/article/ro-reddick-doesnt-mind-if-you-laugh-during-cold-war-choir-practice",
      "image_url": ""
    },
    {
      "title": "Soccer - Non Regulation",
      "venue": "NYC",
      "borough": "NYC",
      "start_iso": "",
      "time_window": "Tonight",
      "url": "https://data.cityofnewyork.us/resource/tvpp-9vvx.json",
      "price": "",
      "category": "city",
      "source_name": "NYC Open Data",
      "source_url": "https://data.cityofnewyork.us/resource/tvpp-9vvx.json",
      "image_url": ""
    },
    {
      "title": "Softball - Adults",
      "venue": "NYC",
      "borough": "NYC",
      "start_iso": "",
      "time_window": "Tonight",
      "url": "https://data.cityofnewyork.us/resource/tvpp-9vvx.json",
      "price": "",
      "category": "city",
      "source_name": "NYC Open Data",
      "source_url": "https://data.cityofnewyork.us/resource/tvpp-9vvx.json",
      "image_url": ""
    },
    {
      "title": "Miscellaneous",
      "venue": "NYC",
      "borough": "NYC",
      "start_iso": "",
      "time_window": "Tonight",
      "url": "https://data.cityofnewyork.us/resource/tvpp-9vvx.json",
      "price": "",
      "category": "city",
      "source_name": "NYC Open Data",
      "source_url": "https://data.cityofnewyork.us/resource/tvpp-9vvx.json",
      "image_url": ""
    },
    {
      "title": "Lawn Closure - East 106th St South Mount Lawn",
      "venue": "NYC",
      "borough": "NYC",
      "start_iso": "",
      "time_window": "Tonight",
      "url": "https://data.cityofnewyork.us/resource/tvpp-9vvx.json",
      "price": "",
      "category": "city",
      "source_name": "NYC Open Data",
      "source_url": "https://data.cityofnewyork.us/resource/tvpp-9vvx.json",
      "image_url": ""
    },
    {
      "title": "Lawn closure - East Meadow",
      "venue": "NYC",
      "borough": "NYC",
      "start_iso": "",
      "time_window": "Tonight",
      "url": "https://data.cityofnewyork.us/resource/tvpp-9vvx.json",
      "price": "",
      "category": "city",
      "source_name": "NYC Open Data",
      "source_url": "https://data.cityofnewyork.us/resource/tvpp-9vvx.json",
      "image_url": ""
    },
    {
      "title": "Baseball - 13 and Older (Little League)",
      "venue": "NYC",
      "borough": "NYC",
      "start_iso": "",
      "time_window": "Tonight",
      "url": "https://data.cityofnewyork.us/resource/tvpp-9vvx.json",
      "price": "",
      "category": "city",
      "source_name": "NYC Open Data",
      "source_url": "https://data.cityofnewyork.us/resource/tvpp-9vvx.json",
      "image_url": ""
    },
    {
      "title": "Gratitude 5k",
      "venue": "NYC",
      "borough": "NYC",
      "start_iso": "",
      "time_window": "Tonight",
      "url": "https://data.cityofnewyork.us/resource/tvpp-9vvx.json",
      "price": "",
      "category": "city",
      "source_name": "NYC Open Data",
      "source_url": "https://data.cityofnewyork.us/resource/tvpp-9vvx.json",
      "image_url": ""
    },
    {
      "title": "Softball (Little league)",
      "venue": "NYC",
      "borough": "NYC",
      "start_iso": "",
      "time_window": "Tonight",
      "url": "https://data.cityofnewyork.us/resource/tvpp-9vvx.json",
      "price": "",
      "category": "city",
      "source_name": "NYC Open Data",
      "source_url": "https://data.cityofnewyork.us/resource/tvpp-9vvx.json",
      "image_url": ""
    },
    {
      "title": "Tennis",
      "venue": "NYC",
      "borough": "NYC",
      "start_iso": "",
      "time_window": "Tonight",
      "url": "https://data.cityofnewyork.us/resource/tvpp-9vvx.json",
      "price": "",
      "category": "city",
      "source_name": "NYC Open Data",
      "source_url": "https://data.cityofnewyork.us/resource/tvpp-9vvx.json",
      "image_url": ""
    },
    {
      "title": "Redbud Lawn Closure",
      "venue": "NYC",
      "borough": "NYC",
      "start_iso": "",
      "time_window": "Tonight",
      "url": "https://data.cityofnewyork.us/resource/tvpp-9vvx.json",
      "price": "",
      "category": "city",
      "source_name": "NYC Open Data",
      "source_url": "https://data.cityofnewyork.us/resource/tvpp-9vvx.json",
      "image_url": ""
    },
    {
      "title": "Free Movies",
      "venue": "NYC",
      "borough": "NYC",
      "start_iso": "",
      "time_window": "Tonight",
      "url": "https://data.cityofnewyork.us/resource/tvpp-9vvx.json",
      "price": "",
      "category": "city",
      "source_name": "NYC Open Data",
      "source_url": "https://data.cityofnewyork.us/resource/tvpp-9vvx.json",
      "image_url": ""
    },
    {
      "title": "Handball",
      "venue": "NYC",
      "borough": "NYC",
      "start_iso": "",
      "time_window": "Tonight",
      "url": "https://data.cityofnewyork.us/resource/tvpp-9vvx.json",
      "price": "",
      "category": "city",
      "source_name": "NYC Open Data",
      "source_url": "https://data.cityofnewyork.us/resource/tvpp-9vvx.json",
      "image_url": ""
    },
    {
      "title": "Soccer -Regulation",
      "venue": "NYC",
      "borough": "NYC",
      "start_iso": "",
      "time_window": "Tonight",
      "url": "https://data.cityofnewyork.us/resource/tvpp-9vvx.json",
      "price": "",
      "category": "city",
      "source_name": "NYC Open Data",
      "source_url": "https://data.cityofnewyork.us/resource/tvpp-9vvx.json",
      "image_url": ""
    },
    {
      "title": "Baseball - 12 and Under (Little League)",
      "venue": "NYC",
      "borough": "NYC",
      "start_iso": "",
      "time_window": "Tonight",
      "url": "https://data.cityofnewyork.us/resource/tvpp-9vvx.json",
      "price": "",
      "category": "city",
      "source_name": "NYC Open Data",
      "source_url": "https://data.cityofnewyork.us/resource/tvpp-9vvx.json",
      "image_url": ""
    },
    {
      "title": "Labsound Amplified Sound DJ Performance",
      "venue": "NYC",
      "borough": "NYC",
      "start_iso": "",
      "time_window": "Tonight",
      "url": "https://data.cityofnewyork.us/resource/tvpp-9vvx.json",
      "price": "",
      "category": "city",
      "source_name": "NYC Open Data",
      "source_url": "https://data.cityofnewyork.us/resource/tvpp-9vvx.json",
      "image_url": ""
    },
    {
      "title": "Kickball",
      "venue": "NYC",
      "borough": "NYC",
      "start_iso": "",
      "time_window": "Tonight",
      "url": "https://data.cityofnewyork.us/resource/tvpp-9vvx.json",
      "price": "",
      "category": "city",
      "source_name": "NYC Open Data",
      "source_url": "https://data.cityofnewyork.us/resource/tvpp-9vvx.json",
      "image_url": ""
    },
    {
      "title": "Barbecue",
      "venue": "NYC",
      "borough": "NYC",
      "start_iso": "",
      "time_window": "Tonight",
      "url": "https://data.cityofnewyork.us/resource/tvpp-9vvx.json",
      "price": "",
      "category": "city",
      "source_name": "NYC Open Data",
      "source_url": "https://data.cityofnewyork.us/resource/tvpp-9vvx.json",
      "image_url": ""
    },
    {
      "title": "Santa's Knights and Gladiators NYC",
      "venue": "NYC",
      "borough": "NYC",
      "start_iso": "",
      "time_window": "Tonight",
      "url": "https://data.cityofnewyork.us/resource/tvpp-9vvx.json",
      "price": "",
      "category": "city",
      "source_name": "NYC Open Data",
      "source_url": "https://data.cityofnewyork.us/resource/tvpp-9vvx.json",
      "image_url": ""
    },
    {
      "title": "Senator Addabbo's Paper Shredding Recycling Event",
      "venue": "NYC",
      "borough": "NYC",
      "start_iso": "",
      "time_window": "Tonight",
      "url": "https://data.cityofnewyork.us/resource/tvpp-9vvx.json",
      "price": "",
      "category": "city",
      "source_name": "NYC Open Data",
      "source_url": "https://data.cityofnewyork.us/resource/tvpp-9vvx.json",
      "image_url": ""
    },
    {
      "title": "QUEENS CANCER WALK",
      "venue": "NYC",
      "borough": "NYC",
      "start_iso": "",
      "time_window": "Tonight",
      "url": "https://data.cityofnewyork.us/resource/tvpp-9vvx.json",
      "price": "",
      "category": "city",
      "source_name": "NYC Open Data",
      "source_url": "https://data.cityofnewyork.us/resource/tvpp-9vvx.json",
      "image_url": ""
    },
    {
      "title": "EsplanadeFriends Fishing Clinic - 2",
      "venue": "NYC",
      "borough": "NYC",
      "start_iso": "",
      "time_window": "Tonight",
      "url": "https://data.cityofnewyork.us/resource/tvpp-9vvx.json",
      "price": "",
      "category": "city",
      "source_name": "NYC Open Data",
      "source_url": "https://data.cityofnewyork.us/resource/tvpp-9vvx.json",
      "image_url": ""
    },
    {
      "title": "NYRR Pre Marathon Youth Event",
      "venue": "NYC",
      "borough": "NYC",
      "start_iso": "",
      "time_window": "Tonight",
      "url": "https://data.cityofnewyork.us/resource/tvpp-9vvx.json",
      "price": "",
      "category": "city",
      "source_name": "NYC Open Data",
      "source_url": "https://data.cityofnewyork.us/resource/tvpp-9vvx.json",
      "image_url": ""
    }
  ],
  "notes": [
    "Featured Tonight now uses real ticketable events only.",
    "Featured Verified requires 2-source verification among real event sources.",
    "Editorial/article links and NYC Open Data city-feed records are excluded from Featured Tonight.",
    "Image fields are included when available for featured cards."
  ]
}